ifs_cloud_parser.cpython-312-x86_64-linux-gnu.so
tree_sitter/parser.h
ifs_cloud_parser-0.2.0.dist-info/METADATA
ifs_cloud_parser-0.2.0.dist-info/WHEEL
ifs_cloud_parser-0.2.0.dist-info/top_level.txt
ifs_cloud_parser-0.2.0.dist-info/RECORD
